civilmod/TKOperation.py
civilmod/__init__.py
civilmod/cm.py
civilmod/forTiger.py
civilmod/tk1.py
civilmod/tk2.py
civilmod/tk3.py
civilmod/tk4.py
civilmod-0.92.52.dist-info/LICENSE
civilmod-0.92.52.dist-info/METADATA
civilmod-0.92.52.dist-info/WHEEL
civilmod-0.92.52.dist-info/top_level.txt
civilmod-0.92.52.dist-info/RECORD
