Metadata-Version: 2.1
Name: civilmod
Version: 0.92.52
Summary: Classic
Home-page: https://nlvac97.github.io
Author: nlvac97
Author-email: ehcemc@outlook.com
License: UNKNOWN
Platform: UNKNOWN
Classifier: Programming Language :: Python :: 3
Classifier: License :: OSI Approved :: MIT License
Classifier: Operating System :: OS Independent
License-File: LICENSE
